nonebot_test/__init__.py
nonebot_test/dist/favicon.ico
nonebot_test/dist/index.html
nonebot_test/dist/static/css/app.0f53224e.css
nonebot_test/dist/static/css/chunk-vendors.c3c2c5a6.css
nonebot_test/dist/static/img/logo.2a63bac0.png
nonebot_test/dist/static/js/app.5fe52bae.js
nonebot_test/dist/static/js/chunk-vendors.4b97ea0d.js
nonebot_test/drivers/fastapi.py
nonebot_test/exception.py
nonebot_test/utils.py
nonebot_test/view.py
nonebot_test-0.1.0.dist-info/LICENSE
nonebot_test-0.1.0.dist-info/WHEEL
nonebot_test-0.1.0.dist-info/METADATA
nonebot_test-0.1.0.dist-info/RECORD
