Metadata-Version: 2.1
Name: nonebot-test
Version: 0.1.0
Summary: Test frontend for nonebot v2+
Home-page: https://v2.nonebot.dev/
License: MIT
Keywords: nonebot,qq,qqbot,mirai,coolq
Author: yanyongyu
Author-email: yanyongyu_1@126.com
Requires-Python: >=3.7,<4.0
Classifier: License :: OSI Approved :: MIT License
Classifier: Programming Language :: Python :: 3
Classifier: Programming Language :: Python :: 3.7
Classifier: Programming Language :: Python :: 3.8
Requires-Dist: aiofiles (>=0.5.0,<0.6.0)
Requires-Dist: nonebot2 (>=2.0.0-alpha.1,<3.0.0)
Requires-Dist: python-socketio (>=4.6.0,<5.0.0)
Project-URL: Repository, https://github.com/nonebot/nonebot-test
